{
  "date": "2026-03-21",
  "generated_at": "20:47",
  "elapsed_seconds": 165,
  "errors": [],
  "stats": {
    "jo_analyses": 1,
    "jo_retenus": 0,
    "articles_presse": 4,
    "depts_restriction": 4,
    "pjl_suivis": 1,
    "pjl_avancements": 0
  },
  "items": [
    {
      "id": "0e6b90035790",
      "source": "Le Monde Planète",
      "categorie": "Climat",
      "titre": "Face à la crise énergétique, accélérer la transition écologique",
      "resume": "L'article souligne l'importance stratégique de la transition écologique pour réduire la dépendance aux énergies fossiles, un enjeu de souveraineté et de résilience face aux chocs géopolitiques. Cela impacte indirectement GSF via les exigences carbone de ses clients (nucléaire, santé, industrie) et les risques climatiques sur ses sites.",
      "pourquoi": "",
      "criticite": 1,
      "impact_gsf": false,
      "url": "https://www.lemonde.fr/idees/article/2026/03/21/face-a-la-crise-energetique-accelerer-la-transition-ecologique_6673255_3232.html",
      "date": "2026-03-21",
      "top5": true
    },
    {
      "id": "896f95178a19",
      "source": "Le Monde Planète",
      "categorie": "Environnement",
      "titre": "Le retour probable d’El Niño fait craindre une aggravation de la crise climatique",
      "resume": "L'article souligne l'aggravation des risques climatiques (températures, événements extrêmes) qui pourraient impacter les 3 000+ sites clients de GSF, notamment en termes de continuité de service et d'adaptation des prestations.",
      "pourquoi": "",
      "criticite": 1,
      "impact_gsf": false,
      "url": "https://www.lemonde.fr/planete/article/2026/03/21/le-retour-probable-d-el-nino-fait-craindre-une-aggravation-de-la-crise-climatique_6673202_3244.html",
      "date": "2026-03-21",
      "top5": true
    },
    {
      "id": "0098d72265b8",
      "source": "EFRAG",
      "categorie": "Énergie",
      "titre": "EFRAG Welcomes a New Friend of EFRAG - Sustainability Reporting: Synesgy",
      "resume": "L'article annonce l'adhésion de Synesgy (plateforme de notation ESG) comme 'Friend of EFRAG', renforçant son engagement dans les normes ESRS de la CSRD. Cela peut impacter les outils de reporting extra-financier de GSF pour ses clients.",
      "pourquoi": "",
      "criticite": 1,
      "impact_gsf": false,
      "url": "https://www.efrag.org/en/news-and-calendar/news/efrag-welcomes-a-new-friend-of-efrag-sustainability-reporting-synesgy",
      "date": "2026-03-21",
      "top5": true
    },
    {
      "id": "52e3d81c8a12",
      "source": "AEF Développement Durable",
      "categorie": "Climat",
      "titre": "À LA UNEComptabilité carbone : les investisseurs soutiennent la révision du GHG Protocol sur le scope 210/03/2026 13:01 - Dépêche n° 746951Quatorze investisseurs représentant plus de 1 200 Md$ d’actif",
      "resume": "La révision du GHG Protocol sur le scope 2 pourrait impacter les exigences de reporting carbone des clients de GSF, notamment dans les secteurs nucléaire, santé et industrie, influençant ainsi les attentes en matière de décarbonation des prestations.",
      "pourquoi": "",
      "criticite": 1,
      "impact_gsf": false,
      "url": "https://www.aefinfo.fr/depeche/746951-comptabilite-carbone-les-investisseurs-soutiennent-la-revision-du-ghg-protocol-sur-le-scope-2",
      "date": "2026-03-21",
      "top5": true
    }
  ],
  "restrictions_eau": [
    {
      "dept_code": "66",
      "dept_nom": "Pyrénées-Orientales",
      "niveau": "crise",
      "niveauSup": "crise",
      "niveauSou": "crise",
      "niveauAep": "crise"
    },
    {
      "dept_code": "2B",
      "dept_nom": "Haute-Corse",
      "niveau": "vigilance",
      "niveauSup": "vigilance",
      "niveauSou": null,
      "niveauAep": "vigilance"
    },
    {
      "dept_code": "972",
      "dept_nom": "Martinique",
      "niveau": "vigilance",
      "niveauSup": "vigilance",
      "niveauSou": null,
      "niveauAep": "vigilance"
    },
    {
      "dept_code": "11",
      "dept_nom": "Aude",
      "niveau": "alerte_renforcee",
      "niveauSup": "alerte_renforcee",
      "niveauSou": "alerte_renforcee",
      "niveauAep": "alerte_renforcee"
    }
  ],
  "jo_autres": [
    {
      "nor": "SPOV2512059L",
      "titre": "LOI n° 2026-201 du 20 mars 2026 relative à l'organisation des jeux Olympiques et Paralympiques de 2030 (1)",
      "nature": "LOI",
      "ministere": "",
      "url": "https://www.legifrance.gouv.fr/jorf/id/JORFTEXT000053707088",
      "date": "2026-03-21"
    },
    {
      "nor": "INTE2607824A",
      "titre": "Arrêté du 19 mars 2026 modifiant l'arrêté du 23 janvier 2025 portant habilitation de la Croix-Rouge française pour les formations aux premiers secours",
      "nature": "ARRETE",
      "ministere": "Ministère de l'intérieur",
      "url": "https://www.legifrance.gouv.fr/jorf/id/JORFTEXT000053707407",
      "date": "2026-03-21"
    },
    {
      "nor": "INTE2607846A",
      "titre": "Arrêté du 19 mars 2026 modifiant l'arrêté du 18 février 2026 portant habilitation de la Fédération nationale des métiers de la natation et du sport pour les formations aux premiers secours",
      "nature": "ARRETE",
      "ministere": "Ministère de l'intérieur",
      "url": "https://www.legifrance.gouv.fr/jorf/id/JORFTEXT000053707419",
      "date": "2026-03-21"
    },
    {
      "nor": "JUST2607468A",
      "titre": "Arrêté du 18 mars 2026 fixant les taux de promotion dans le corps des secrétaires administratifs du ministère de la justice pour l'année 2027",
      "nature": "ARRETE",
      "ministere": "Ministère de la justice",
      "url": "https://www.legifrance.gouv.fr/jorf/id/JORFTEXT000053707470",
      "date": "2026-03-21"
    },
    {
      "nor": "RCAR2608032S",
      "titre": "Décision n° 2026-NA-08 du 2 mars 2026 autorisant l'Association départementale des Francas de Meurthe-et-Moselle à exploiter un service de radio temporaire par voie hertzienne terrestre en modulation de fréquence dénommé Radio Francas",
      "nature": "DECISION",
      "ministere": "",
      "url": "https://www.legifrance.gouv.fr/jorf/id/JORFTEXT000053707652",
      "date": "2026-03-21"
    },
    {
      "nor": "RIAH2602991A",
      "titre": "Arrêté du 17 mars 2026 autorisant au titre de l'année 2025 l'ouverture de concours externes pour le recrutement de techniciens de la recherche de classe normale à l'Institut national de recherche en informatique et en automatique (INRIA)",
      "nature": "ARRETE",
      "ministere": "",
      "url": "https://www.legifrance.gouv.fr/jorf/id/JORFTEXT000053707669",
      "date": "2026-03-21"
    },
    {
      "nor": "ARMA2607883V",
      "titre": "Avis d'ouverture du concours sur titres pour le recrutement au grade d'ingénieur dans le corps militaire des ingénieurs des études et techniques de l'armement au titre de l'année 2026",
      "nature": "AVIS",
      "ministere": "Ministère des armées et des anciens combattants",
      "url": "https://www.legifrance.gouv.fr/jorf/id/JORFTEXT000053707713",
      "date": "2026-03-21"
    },
    {
      "nor": "ARMA2607888V",
      "titre": "Avis d'ouverture du concours sur titres pour le recrutement de titulaires d'un doctorat au premier échelon du premier grade d'ingénieur dans le corps militaire des ingénieurs de l'armement au titre de l'année 2026",
      "nature": "AVIS",
      "ministere": "Ministère des armées et des anciens combattants",
      "url": "https://www.legifrance.gouv.fr/jorf/id/JORFTEXT000053707724",
      "date": "2026-03-21"
    },
    {
      "nor": "ARMA2607901V",
      "titre": "Avis d'ouverture du concours sur titres pour le recrutement au premier échelon du premier grade d'ingénieur dans le corps militaire des ingénieurs de l'armement au titre de l'année 2026",
      "nature": "AVIS",
      "ministere": "Ministère des armées et des anciens combattants",
      "url": "https://www.legifrance.gouv.fr/jorf/id/JORFTEXT000053707735",
      "date": "2026-03-21"
    },
    {
      "nor": "ARMA2607294A",
      "titre": "Arrêté du 11 mars 2026 fixant les conditions d'organisation et de déroulement du concours externe pour le recrutement réservé aux titulaires d'un diplôme de doctorat au premier échelon du premier grade d'ingénieur dans le corps militaire des ingénieurs de l'armement",
      "nature": "ARRETE",
      "ministere": "Ministère des armées et des anciens combattants",
      "url": "https://www.legifrance.gouv.fr/jorf/id/JORFTEXT000053685034",
      "date": "2026-03-18"
    },
    {
      "nor": "CSCL2607931S",
      "titre": "Décision n° 2026-902 DC du 19 mars 2026",
      "nature": "DECISION",
      "ministere": "",
      "url": "https://www.legifrance.gouv.fr/jorf/id/JORFTEXT000053707307",
      "date": "2026-03-21"
    },
    {
      "nor": "INTC2607639A",
      "titre": "Arrêté du 3 mars 2026 modifiant l'arrêté du 20 janvier 2022 fixant la liste des emplois ouvrant droit à l'indemnité temporaire de mobilité au sein du ministère de l'intérieur",
      "nature": "ARRETE",
      "ministere": "",
      "url": "https://www.legifrance.gouv.fr/jorf/id/JORFTEXT000053707380",
      "date": "2026-03-21"
    },
    {
      "nor": "INTD2606843A",
      "titre": "Arrêté du 19 mars 2026 portant interdiction de déplacement des supporters du club de football du Lille Olympique Sporting Club lors de la rencontre du dimanche 22 mars 2026 à 17 h 15 avec l'Olympique de Marseille",
      "nature": "ARRETE",
      "ministere": "",
      "url": "https://www.legifrance.gouv.fr/jorf/id/JORFTEXT000053707396",
      "date": "2026-03-21"
    },
    {
      "nor": "TRST2606349A",
      "titre": "Arrêté du 19 mars 2026 portant agrément de l'accord du 13 novembre 2025 proposant un accord-type d'intéressement dans la branche des caves coopératives vinicoles et leurs unions",
      "nature": "ARRETE",
      "ministere": "",
      "url": "https://www.legifrance.gouv.fr/jorf/id/JORFTEXT000053707442",
      "date": "2026-03-21"
    },
    {
      "nor": "TRST2607346A",
      "titre": "Arrêté du 19 mars 2026 portant agrément de l'accord du 20 février 2026 portant mise en place de l'intéressement dans la branche de la métallurgie",
      "nature": "ARRETE",
      "ministere": "",
      "url": "https://www.legifrance.gouv.fr/jorf/id/JORFTEXT000053707451",
      "date": "2026-03-21"
    },
    {
      "nor": "TRST2607416A",
      "titre": "Arrêté du 19 mars 2026 portant agrément de l'accord du 20 février 2026 portant mise en place de la participation dans la branche de la métallurgie",
      "nature": "ARRETE",
      "ministere": "",
      "url": "https://www.legifrance.gouv.fr/jorf/id/JORFTEXT000053707460",
      "date": "2026-03-21"
    },
    {
      "nor": "JUSF2607578A",
      "titre": "Arrêté du 19 mars 2026 portant modification du montant de l'avance de la régie auprès de la direction territoriale de la protection judiciaire de la jeunesse de Franche-Comté",
      "nature": "ARRETE",
      "ministere": "",
      "url": "https://www.legifrance.gouv.fr/jorf/id/JORFTEXT000053707482",
      "date": "2026-03-21"
    },
    {
      "nor": "JUSF2607579A",
      "titre": "Arrêté du 19 mars 2026 portant modification du montant de l'avance de la régie auprès de la direction territoriale de la protection judiciaire de la jeunesse de Touraine-Berry",
      "nature": "ARRETE",
      "ministere": "",
      "url": "https://www.legifrance.gouv.fr/jorf/id/JORFTEXT000053707492",
      "date": "2026-03-21"
    },
    {
      "nor": "JUSF2607581A",
      "titre": "Arrêté du 19 mars 2026 portant modification du montant de l'avance de la régie auprès de la direction territoriale de la protection judiciaire de la jeunesse de l'Yonne-Nièvre",
      "nature": "ARRETE",
      "ministere": "",
      "url": "https://www.legifrance.gouv.fr/jorf/id/JORFTEXT000053707502",
      "date": "2026-03-21"
    },
    {
      "nor": "ATDB2603335A",
      "titre": "Arrêté du 12 mars 2026 pris pour l'application en 2026 de l'article L. 1614-4 du code général des collectivités territoriales",
      "nature": "ARRETE",
      "ministere": "",
      "url": "https://www.legifrance.gouv.fr/jorf/id/JORFTEXT000053707518",
      "date": "2026-03-21"
    },
    {
      "nor": "CPPD2607975A",
      "titre": "Arrêté du 20 mars 2026 fixant au titre de l'année 2026 le nombre de places offertes au concours professionnel pour l'accès au grade de contrôleur de 1re classe des douanes et droits indirects",
      "nature": "ARRETE",
      "ministere": "",
      "url": "https://www.legifrance.gouv.fr/jorf/id/JORFTEXT000053707526",
      "date": "2026-03-21"
    },
    {
      "nor": "PRMG2607519A",
      "titre": "Arrêté du 19 mars 2026 modifiant l'arrêté du 6 juillet 2023 relatif à la composition de l'instance collégiale d'évaluation des cadres supérieurs au sein des services du Premier ministre",
      "nature": "ARRETE",
      "ministere": "",
      "url": "https://www.legifrance.gouv.fr/jorf/id/JORFTEXT000053707544",
      "date": "2026-03-21"
    },
    {
      "nor": "INTP2606286A",
      "titre": "Arrêté du 19 mars 2026 portant nomination (administration centrale)",
      "nature": "ARRETE",
      "ministere": "",
      "url": "https://www.legifrance.gouv.fr/jorf/id/JORFTEXT000053707560",
      "date": "2026-03-21"
    },
    {
      "nor": "INTP2607687A",
      "titre": "Arrêté du 19 mars 2026 portant nomination (directions départementales interministérielles)",
      "nature": "ARRETE",
      "ministere": "",
      "url": "https://www.legifrance.gouv.fr/jorf/id/JORFTEXT000053707565",
      "date": "2026-03-21"
    },
    {
      "nor": "ESRS2603532A",
      "titre": "Arrêté du 10 mars 2026 portant nomination à la commission instituée à l'article 51-1 du décret n° 91-1197 du 27 novembre 1991 organisant la profession d'avocat",
      "nature": "ARRETE",
      "ministere": "",
      "url": "https://www.legifrance.gouv.fr/jorf/id/JORFTEXT000053707591",
      "date": "2026-03-21"
    },
    {
      "nor": "TRST2607668V",
      "titre": "Avis relatif à l'extension d'avenants et d'un avenant à un accord conclus dans le cadre de la convention collective nationale de la transformation des grains",
      "nature": "AVIS",
      "ministere": "",
      "url": "https://www.legifrance.gouv.fr/jorf/id/JORFTEXT000053707599",
      "date": "2026-03-21"
    },
    {
      "nor": "TRST2607669V",
      "titre": "Avis relatif à l'extension d'accords conclus dans le cadre de la convention collective nationale de l'édition",
      "nature": "AVIS",
      "ministere": "",
      "url": "https://www.legifrance.gouv.fr/jorf/id/JORFTEXT000053707605",
      "date": "2026-03-21"
    },
    {
      "nor": "CSCX2607960S",
      "titre": "Décision n° 2025-1187 QPC du 20 mars 2026",
      "nature": "DECISION",
      "ministere": "",
      "url": "https://www.legifrance.gouv.fr/jorf/id/JORFTEXT000053707611",
      "date": "2026-03-21"
    },
    {
      "nor": "INTN2605317D",
      "titre": "Décret du 10 mars 2026 portant naturalisation, réintégration, mention d'enfants mineurs bénéficiant de l'effet collectif attaché à l'acquisition de la nationalité française par leurs parents, francisation de noms et de prénoms et libération de l'allégeance française (Accès protégé)",
      "nature": "DECRET",
      "ministere": "",
      "url": "https://www.legifrance.gouv.fr/jorf/id/JORFTEXT000053707696",
      "date": "2026-03-21"
    },
    {
      "nor": "SFHS2607882V",
      "titre": "Avis relatif à une vacance de poste de directeur de caisse de sécurité sociale",
      "nature": "AVIS",
      "ministere": "",
      "url": "https://www.legifrance.gouv.fr/jorf/id/JORFTEXT000053707749",
      "date": "2026-03-21"
    },
    {
      "nor": "MICC2607811V",
      "titre": "Avis n° 2026-02 de la Commission consultative des trésors nationaux",
      "nature": "AVIS",
      "ministere": "",
      "url": "https://www.legifrance.gouv.fr/jorf/id/JORFTEXT000053707758",
      "date": "2026-03-21"
    },
    {
      "nor": "ARMH2607224A",
      "titre": "Arrêté du 13 mars 2026 relatif au recrutement par certains concours au premier grade d'ingénieur dans le corps militaire des ingénieurs de l'armement",
      "nature": "ARRETE",
      "ministere": "",
      "url": "https://www.legifrance.gouv.fr/jorf/id/JORFTEXT000053671478",
      "date": "2026-03-15"
    },
    {
      "nor": "ARMD2606902D",
      "titre": "Décret n° 2026-202 du 20 mars 2026 portant prorogation du mandat des membres de la commission nationale indépendante de reconnaissance et de réparation des préjudices subis par les harkis, les autres personnes rapatriées d'Algérie anciennement de statut civil de droit local et les membres de leurs familles",
      "nature": "DECRET",
      "ministere": "",
      "url": "https://www.legifrance.gouv.fr/jorf/id/JORFTEXT000053707432",
      "date": "2026-03-21"
    }
  ],
  "jo_retenus": [],
  "briefing_jorf": "Aucun lien direct avec les enjeux Environnement/Climat ou la RSE n'est identifiable dans ce décret relatif aux harkis et rapatriés d'Algérie.",
  "pjl_fiches": [
    {
      "id": "pjl-14aebd68935a",
      "titre": "Projet de loi portant diverses dispositions d'adaptation au droit de l’Union européenne en matière économique, financière, environnementale, énergétique, d’information, de transport, de santé, d’agriculture et de pêche - N° 2518",
      "date_depot": "2026-03-20",
      "stade": "Première lecture à l'Assemblée nationale",
      "stade_index": 2,
      "url_an": "https://www.assemblee-nationale.fr/dyn/17/dossiers/DLR5L17N53140",
      "url_dossier": "https://www.assemblee-nationale.fr/dyn/17/dossiers/DLR5L17N53140",
      "source_rss": "pipeline",
      "resume_gsf": null,
      "pourquoi": null,
      "score": 2,
      "horizon": "Début 2025 (transposition des directives européennes, entrée en vigueur progressive à partir de 2025-2026)",
      "nouveau_stade": false,
      "manuel": false,
      "historique": [],
      "created_at": "2026-03-20T23:57:18.140824+00:00",
      "updated_at": "2026-03-21T20:27:48.856604+00:00",
      "supabase_id": "ab2fc271-9dc3-42f0-8185-9215c1039c06",
      "statut": "pour_info"
    }
  ],
  "pjl_autres": [
    {
      "source": "AN Projets de loi",
      "items": [
        {
          "titre": "Projet de loi portant diverses dispositions d'adaptation au droit de l’Union européenne en matière économique, financière, environnementale, énergétique, d’information, de transport, de santé, d’agriculture et de pêche - N° 2518",
          "url": "https://www.assemblee-nationale.fr/dyn/17/dossiers/DLR5L17N53140",
          "url_dossier": "https://www.assemblee-nationale.fr/dyn/17/dossiers/DLR5L17N53140",
          "date": "2025-11-10"
        },
        {
          "titre": "Projet de loi constitutionnelle relatif à la Nouvelle-Calédonie - N° 2529",
          "url": "https://www.assemblee-nationale.fr/dyn/17/dossiers/DLR5L17N52984",
          "url_dossier": "https://www.assemblee-nationale.fr/dyn/17/dossiers/DLR5L17N52984",
          "date": "2025-10-14"
        },
        {
          "titre": "Projet de loi de financement de la sécurité sociale pour 2026 - N° 2242",
          "url": "https://www.assemblee-nationale.fr/dyn/17/dossiers/PLFSS_2026",
          "url_dossier": "https://www.assemblee-nationale.fr/dyn/17/dossiers/PLFSS_2026",
          "date": "2025-10-14"
        },
        {
          "titre": "Projet de loi autorisant l’approbation de la convention entre le Gouvernement de la République française et le Gouvernement de la République de Chypre pour l’élimination de la double imposition en matière d’impôts sur le revenu et la prévention de l’évasion et de la fraude fiscales - N° 2516",
          "url": "https://www.assemblee-nationale.fr/dyn/17/dossiers/DLR5L17N53706",
          "url_dossier": "https://www.assemblee-nationale.fr/dyn/17/dossiers/DLR5L17N53706",
          "date": "2026-01-28"
        },
        {
          "titre": "Projet de loi autorisant l'approbation de la Convention entre le Gouvernement de la République française et le Gouvernement de la République italienne relative à l’entretien courant et à l’exploitation de la section située en territoire français de la lign - N° 2510",
          "url": "https://www.assemblee-nationale.fr/dyn/17/dossiers/DLR5L17N53730",
          "url_dossier": "https://www.assemblee-nationale.fr/dyn/17/dossiers/DLR5L17N53730",
          "date": "2026-02-04"
        },
        {
          "titre": "Projet de loi autorisant l’approbation de la convention d’extradition entre le Gouvernement de la République française et le Gouvernement de la République de Colombie - N° 2509",
          "url": "https://www.assemblee-nationale.fr/dyn/17/dossiers/DLR5L17N53095",
          "url_dossier": "https://www.assemblee-nationale.fr/dyn/17/dossiers/DLR5L17N53095",
          "date": "2025-10-29"
        },
        {
          "titre": "Projet de loi autorisant l’approbation de l’accord entre le Gouvernement de la République française et le Gouvernement de la République de Moldavie dans le domaine de la sécurité sociale - N° 2471",
          "url": "https://www.assemblee-nationale.fr/dyn/17/dossiers/moldavie_securite_sociale",
          "url_dossier": "https://www.assemblee-nationale.fr/dyn/17/dossiers/moldavie_securite_sociale",
          "date": "2026-02-11"
        },
        {
          "titre": "Projet de loi relatif à l’extension des prérogatives, des moyens, de l’organisation et du contrôle des polices municipales et des gardes champêtres - N° 2464",
          "url": "https://www.assemblee-nationale.fr/dyn/17/dossiers/DLR5L17N53096",
          "url_dossier": "https://www.assemblee-nationale.fr/dyn/17/dossiers/DLR5L17N53096",
          "date": "2025-10-29"
        },
        {
          "titre": "Projet de loi autorisant l’approbation de l’accord entre le Gouvernement de la République française et la Communauté des Caraïbes relatif à l’adhésion au protocole sur les privilèges et immunités de la Communauté des Caraïbes du 14 janvier 1985 - N° 2414",
          "url": "https://www.assemblee-nationale.fr/dyn/17/dossiers/DLR5L17N53235",
          "url_dossier": "https://www.assemblee-nationale.fr/dyn/17/dossiers/DLR5L17N53235",
          "date": "2025-11-26"
        },
        {
          "titre": "Projet de loi autorisant l’approbation de l’accord entre le Gouvernement de la République française et le Gouvernement de la République du Kazakhstan sur la réadmission des personnes - N° 2416",
          "url": "https://www.assemblee-nationale.fr/dyn/17/dossiers/DLR5L17N53388",
          "url_dossier": "https://www.assemblee-nationale.fr/dyn/17/dossiers/DLR5L17N53388",
          "date": "2025-12-17"
        },
        {
          "titre": "Projet de loi relatif à la restitution de biens culturels provenant d’États qui, du fait d’une appropriation illicite, en ont été privés - N° 2408",
          "url": "https://www.assemblee-nationale.fr/dyn/17/dossiers/DLR5L17N52635",
          "url_dossier": "https://www.assemblee-nationale.fr/dyn/17/dossiers/DLR5L17N52635",
          "date": "2025-07-30"
        },
        {
          "titre": "Projet de loi autorisant l’approbation de l’accord entre le Gouvernement de la République française et le Gouvernement de la République de Moldova relatif à la coopération dans le domaine de la défense - N° 2050",
          "url": "https://www.assemblee-nationale.fr/dyn/17/dossiers/projet_loi_autorisant_approbation_accord_gouvernement_moldova_defense",
          "url_dossier": "https://www.assemblee-nationale.fr/dyn/17/dossiers/projet_loi_autorisant_approbation_accord_gouvernement_moldova_defense",
          "date": "2025-10-29"
        },
        {
          "titre": "Projet de loi spéciale prévue par l'article 45 de la loi organique n°2001-692 du 1er août 2001 relative aux lois de finances - N° 2269",
          "url": "https://www.assemblee-nationale.fr/dyn/17/dossiers/loi_speciale_2026",
          "url_dossier": "https://www.assemblee-nationale.fr/dyn/17/dossiers/loi_speciale_2026",
          "date": "2025-12-22"
        },
        {
          "titre": "Projet de loi de finances pour 2026 - N° 2247",
          "url": "https://www.assemblee-nationale.fr/dyn/17/dossiers/PLF_2026",
          "url_dossier": "https://www.assemblee-nationale.fr/dyn/17/dossiers/PLF_2026",
          "date": "2025-10-14"
        },
        {
          "titre": "Projet de loi autorisant l’approbation de l’accord entre le Gouvernement de la République française et le Gouvernement du Monténégro relatif à la coopération dans le domaine de la défense - N° 2236",
          "url": "https://www.assemblee-nationale.fr/dyn/17/dossiers/DLR5L17N52561",
          "url_dossier": "https://www.assemblee-nationale.fr/dyn/17/dossiers/DLR5L17N52561",
          "date": "2025-07-16"
        },
        {
          "titre": "L’approbation de l’accord entre le Gouvernement de la République française et l’Agence spatiale européenne concernant les installations de l’Agence spatiale européenne en France - N° 2155",
          "url": "https://www.assemblee-nationale.fr/dyn/17/dossiers/approbation_accord_Gouvernement_Agence_spatiale_europeenne_installations_France",
          "url_dossier": "https://www.assemblee-nationale.fr/dyn/17/dossiers/approbation_accord_Gouvernement_Agence_spatiale_europeenne_installations_France",
          "date": "2025-12-02"
        },
        {
          "titre": "Projet de loi de finances de fin de gestion pour 2025 - N° 2135",
          "url": "https://www.assemblee-nationale.fr/dyn/17/dossiers/projet_de_loi_de_finances_de_fin_de_gestion_pour_2025",
          "url_dossier": "https://www.assemblee-nationale.fr/dyn/17/dossiers/projet_de_loi_de_finances_de_fin_de_gestion_pour_2025",
          "date": "2025-11-10"
        },
        {
          "titre": "Projet de loi relatif à la lutte contre les fraudes sociales et fiscales - N° 2115",
          "url": "https://www.assemblee-nationale.fr/dyn/17/dossiers/DLR5L17N52985",
          "url_dossier": "https://www.assemblee-nationale.fr/dyn/17/dossiers/DLR5L17N52985",
          "date": "2025-10-14"
        },
        {
          "titre": "Projet de loi de lutte contre la vie chère dans les outre-mer - N° 2046",
          "url": "https://www.assemblee-nationale.fr/dyn/17/dossiers/DLR5L17N52600",
          "url_dossier": "https://www.assemblee-nationale.fr/dyn/17/dossiers/DLR5L17N52600",
          "date": "2025-07-30"
        },
        {
          "titre": "Projet de loi autorisant l’approbation de la convention entre le Gouvernement de la République française et le Gouvernement de la République de Finlande pour l’élimination de la double imposition en matière d’impôts sur le revenu et la prévention de l’évasion et de la fraude fiscales et l’approbation de l’avenant à la convention entre le Gouvernement de la République française et le Gouvernement du Royaume de Suède en vue d’éviter les doubles impositions et de prévenir l’évasion fiscale en matière d’impôts sur le revenu et sur la fortune - N° 2054",
          "url": "https://www.assemblee-nationale.fr/dyn/17/dossiers/DLR5L17N52549",
          "url_dossier": "https://www.assemblee-nationale.fr/dyn/17/dossiers/DLR5L17N52549",
          "date": "2025-07-11"
        },
        {
          "titre": "Projet de loi autorisant l’approbation de l’accord sous forme d’échange de notes verbales entre le Gouvernement de la République française et le Gouvernement de la République de Moldavie relatif à l'échange de permis de conduire - N° 2053",
          "url": "https://www.assemblee-nationale.fr/dyn/17/dossiers/DLR5L17N52354",
          "url_dossier": "https://www.assemblee-nationale.fr/dyn/17/dossiers/DLR5L17N52354",
          "date": "2025-06-19"
        },
        {
          "titre": "Projet de loi relatif à la régulation de l'enseignement supérieur privé - N° 1762",
          "url": "https://www.assemblee-nationale.fr/dyn/17/dossiers/projet_de_loi_regulation_enseignement_superieur_prive",
          "url_dossier": "https://www.assemblee-nationale.fr/dyn/17/dossiers/projet_de_loi_regulation_enseignement_superieur_prive",
          "date": "2025-07-31"
        },
        {
          "titre": "Projet de loi autorisant l’approbation de la convention de coopération judiciaire internationale entre la France et le Myanmar - N° 1664",
          "url": "https://www.assemblee-nationale.fr/dyn/17/dossiers/cooperation_judiciaire_France_Myanmar",
          "url_dossier": "https://www.assemblee-nationale.fr/dyn/17/dossiers/cooperation_judiciaire_France_Myanmar",
          "date": "2025-07-02"
        },
        {
          "titre": "Projet de loi relatif à l’organisation des jeux Olympiques et Paralympiques de 2030 - N° 1641",
          "url": "https://www.assemblee-nationale.fr/dyn/17/dossiers/DLR5L17N52100",
          "url_dossier": "https://www.assemblee-nationale.fr/dyn/17/dossiers/DLR5L17N52100",
          "date": "2025-05-15"
        },
        {
          "titre": "Projet de loi autorisant l’approbation de la convention d’entraide judiciaire en matière pénale entre le Gouvernement de la République française et le Gouvernement de la République du Suriname - N° 1616",
          "url": "https://www.assemblee-nationale.fr/dyn/17/dossiers/DLR5L17N52000",
          "url_dossier": "https://www.assemblee-nationale.fr/dyn/17/dossiers/DLR5L17N52000",
          "date": "2025-04-28"
        },
        {
          "titre": "Projet de loi autorisant l’approbation de l’avenant à la convention d’entraide judiciaire en matière pénale du 28 mai 1996 entre le Gouvernement de la République française et le Gouvernement de la République fédérative du Brésil - N° 1614",
          "url": "https://www.assemblee-nationale.fr/dyn/17/dossiers/DLR5L17N52103",
          "url_dossier": "https://www.assemblee-nationale.fr/dyn/17/dossiers/DLR5L17N52103",
          "date": "2025-05-15"
        }
      ]
    },
    {
      "source": "AN Textes adoptés",
      "items": [
        {
          "titre": "Texte adopté N° 248",
          "url": "https://www.assemblee-nationale.fr/dyn/17/dossiers/allocations_chomage_travailleurs_frontaliers",
          "url_dossier": "https://www.assemblee-nationale.fr/dyn/17/dossiers/allocations_chomage_travailleurs_frontaliers",
          "date": "2026-03-21"
        },
        {
          "titre": "Texte adopté N° 247",
          "url": "https://www.assemblee-nationale.fr/dyn/17/dossiers/affiliation_sociale_enfants_travailleurs_frontaliers",
          "url_dossier": "https://www.assemblee-nationale.fr/dyn/17/dossiers/affiliation_sociale_enfants_travailleurs_frontaliers",
          "date": "2025-07-22"
        },
        {
          "titre": "Texte adopté N° 246",
          "url": "https://www.assemblee-nationale.fr/dyn/17/dossiers/teletravail-frontalier",
          "url_dossier": "https://www.assemblee-nationale.fr/dyn/17/dossiers/teletravail-frontalier",
          "date": "2025-07-22"
        },
        {
          "titre": "Texte adopté N° 243",
          "url": "https://www.assemblee-nationale.fr/dyn/17/dossiers/fin_de_vie_17e",
          "url_dossier": "https://www.assemblee-nationale.fr/dyn/17/dossiers/fin_de_vie_17e",
          "date": "2025-03-11"
        },
        {
          "titre": "Texte adopté N° 242",
          "url": "https://www.assemblee-nationale.fr/dyn/17/dossiers/soins_palliatifs_et_accompagnement_17e",
          "url_dossier": "https://www.assemblee-nationale.fr/dyn/17/dossiers/soins_palliatifs_et_accompagnement_17e",
          "date": "2025-03-11"
        },
        {
          "titre": "Texte adopté N° 241",
          "url": "https://www.assemblee-nationale.fr/dyn/17/dossiers/enseignement_education_alimentation_17e",
          "url_dossier": "https://www.assemblee-nationale.fr/dyn/17/dossiers/enseignement_education_alimentation_17e",
          "date": "2025-11-18"
        },
        {
          "titre": "Texte adopté N° 240",
          "url": "https://www.assemblee-nationale.fr/dyn/17/dossiers/extension-possibilite_preemption_baux_commerciaux_mairies_societes_civiles_immobilieres_17e",
          "url_dossier": "https://www.assemblee-nationale.fr/dyn/17/dossiers/extension-possibilite_preemption_baux_commerciaux_mairies_societes_civiles_immobilieres_17e",
          "date": "2025-03-18"
        },
        {
          "titre": "Texte adopté N° 239",
          "url": "https://www.assemblee-nationale.fr/dyn/17/dossiers/protection_commercants_outils_numeriques_17e",
          "url_dossier": "https://www.assemblee-nationale.fr/dyn/17/dossiers/protection_commercants_outils_numeriques_17e",
          "date": "2025-03-18"
        },
        {
          "titre": "Texte adopté N° 238",
          "url": "https://www.assemblee-nationale.fr/dyn/17/dossiers/renforcer_pilotage_coherence_politique_nationale_sport",
          "url_dossier": "https://www.assemblee-nationale.fr/dyn/17/dossiers/renforcer_pilotage_coherence_politique_nationale_sport",
          "date": "2025-11-20"
        },
        {
          "titre": "Texte adopté N° 237",
          "url": "https://www.assemblee-nationale.fr/dyn/17/dossiers/faciliter_exercice_france_medecins_diplomes_royaume_uni_avant_brexit_17e",
          "url_dossier": "https://www.assemblee-nationale.fr/dyn/17/dossiers/faciliter_exercice_france_medecins_diplomes_royaume_uni_avant_brexit_17e",
          "date": "2025-11-18"
        },
        {
          "titre": "Texte adopté N° 236",
          "url": "https://www.assemblee-nationale.fr/dyn/17/dossiers/ameliorer_protection_personnes_ciblees_reseaux_criminalite_organisee_17e",
          "url_dossier": "https://www.assemblee-nationale.fr/dyn/17/dossiers/ameliorer_protection_personnes_ciblees_reseaux_criminalite_organisee_17e",
          "date": "2025-12-23"
        },
        {
          "titre": "Texte adopté N° 235",
          "url": "https://www.assemblee-nationale.fr/dyn/17/dossiers/relancer_investissements_secteur_hydroelectricite_contribuer_transition_energetique_17e",
          "url_dossier": "https://www.assemblee-nationale.fr/dyn/17/dossiers/relancer_investissements_secteur_hydroelectricite_contribuer_transition_energetique_17e",
          "date": "2026-01-13"
        },
        {
          "titre": "Texte adopté N° 234",
          "url": "https://www.assemblee-nationale.fr/dyn/17/dossiers/reaffirmer_ambition_climatique_France_europeen",
          "url_dossier": "https://www.assemblee-nationale.fr/dyn/17/dossiers/reaffirmer_ambition_climatique_France_europeen",
          "date": "2025-10-23"
        },
        {
          "titre": "Texte adopté N° 233",
          "url": "https://www.assemblee-nationale.fr/dyn/17/dossiers/rejeter_accord_douane_commerce_UE_Etats_Unis",
          "url_dossier": "https://www.assemblee-nationale.fr/dyn/17/dossiers/rejeter_accord_douane_commerce_UE_Etats_Unis",
          "date": "2025-07-30"
        },
        {
          "titre": "Texte adopté N° 230",
          "url": "https://www.assemblee-nationale.fr/dyn/17/dossiers/lutte_VIH_SIDA_UE",
          "url_dossier": "https://www.assemblee-nationale.fr/dyn/17/dossiers/lutte_VIH_SIDA_UE",
          "date": "2025-03-13"
        },
        {
          "titre": "Texte adopté N° 231",
          "url": "https://www.assemblee-nationale.fr/dyn/17/dossiers/soutenir_danemark_groenland_oeuvrer_cooperation_defense",
          "url_dossier": "https://www.assemblee-nationale.fr/dyn/17/dossiers/soutenir_danemark_groenland_oeuvrer_cooperation_defense",
          "date": "2025-03-25"
        },
        {
          "titre": "Texte adopté N° 229",
          "url": "https://www.assemblee-nationale.fr/dyn/17/dossiers/prisonniers_armeniens_liberation",
          "url_dossier": "https://www.assemblee-nationale.fr/dyn/17/dossiers/prisonniers_armeniens_liberation",
          "date": "2025-12-19"
        },
        {
          "titre": "Texte adopté N° 232",
          "url": "https://www.assemblee-nationale.fr/dyn/17/dossiers/Turquie_etat_droit2",
          "url_dossier": "https://www.assemblee-nationale.fr/dyn/17/dossiers/Turquie_etat_droit2",
          "date": "2025-04-04"
        },
        {
          "titre": "Texte adopté N° 226",
          "url": "https://www.assemblee-nationale.fr/dyn/17/dossiers/interet_des_enfants_17",
          "url_dossier": "https://www.assemblee-nationale.fr/dyn/17/dossiers/interet_des_enfants_17",
          "date": "2025-03-11"
        },
        {
          "titre": "Texte adopté N° 225",
          "url": "https://www.assemblee-nationale.fr/dyn/17/dossiers/victimes_exposition_essais_nucleaires_ameliorer_indemnisation_17e",
          "url_dossier": "https://www.assemblee-nationale.fr/dyn/17/dossiers/victimes_exposition_essais_nucleaires_ameliorer_indemnisation_17e",
          "date": "2025-12-02"
        },
        {
          "titre": "Texte adopté N° 224",
          "url": "https://www.assemblee-nationale.fr/dyn/17/dossiers/gratuite_parkings_hopitaux_17e",
          "url_dossier": "https://www.assemblee-nationale.fr/dyn/17/dossiers/gratuite_parkings_hopitaux_17e",
          "date": "2025-09-16"
        },
        {
          "titre": "Texte adopté N° 222",
          "url": "https://www.assemblee-nationale.fr/dyn/17/dossiers/_mettre_fin_au_devoir_conjugual_17e",
          "url_dossier": "https://www.assemblee-nationale.fr/dyn/17/dossiers/_mettre_fin_au_devoir_conjugual_17e",
          "date": "2025-12-02"
        },
        {
          "titre": "Texte adopté N° 223",
          "url": "https://www.assemblee-nationale.fr/dyn/17/dossiers/reparer_prejudices_transplantation_mineurs_la_reunion_17e",
          "url_dossier": "https://www.assemblee-nationale.fr/dyn/17/dossiers/reparer_prejudices_transplantation_mineurs_la_reunion_17e",
          "date": "2026-03-21"
        },
        {
          "titre": "Texte adopté N° 221",
          "url": "https://www.assemblee-nationale.fr/dyn/17/dossiers/gestion_patrimoine_immobilier_etat_17e",
          "url_dossier": "https://www.assemblee-nationale.fr/dyn/17/dossiers/gestion_patrimoine_immobilier_etat_17e",
          "date": "2025-09-16"
        },
        {
          "titre": "Texte adopté N° 220",
          "url": "https://www.assemblee-nationale.fr/dyn/17/dossiers/traitement_judiciaire_violences_sexuelles_incestueuses_parentales_contre_enfants_situation_parents_protecteurs_meres_protectrices",
          "url_dossier": "https://www.assemblee-nationale.fr/dyn/17/dossiers/traitement_judiciaire_violences_sexuelles_incestueuses_parentales_contre_enfants_situation_parents_protecteurs_meres_protectrices",
          "date": "2025-10-20"
        },
        {
          "titre": "Texte adopté N° 219",
          "url": "https://www.assemblee-nationale.fr/dyn/17/dossiers/acces_emploi_experimentation_tzcld_17",
          "url_dossier": "https://www.assemblee-nationale.fr/dyn/17/dossiers/acces_emploi_experimentation_tzcld_17",
          "date": "2025-04-17"
        }
      ]
    }
  ],
  "pjl_briefing": "Le projet de loi n°2518 portant adaptation au droit de l’UE en matière environnementale et énergétique est le seul texte directement pertinent pour un Responsable Environnement/Climat, avec des implications potentielles sur la réglementation climatique, la transition énergétique et les obligations de reporting RSE. Aucun autre texte adopté ou en discussion ne traite spécifiquement de sujets environnementaux ou climatiques."
}